jooxy/__init__.py
jooxy/auth.py
jooxy/client.py
jooxy/config.py
jooxy/sessions.py
jooxy/user.py
jooxy/utils.py
jooxy-1.0.4.dist-info/LICENSE
jooxy-1.0.4.dist-info/METADATA
jooxy-1.0.4.dist-info/WHEEL
jooxy-1.0.4.dist-info/top_level.txt
jooxy-1.0.4.dist-info/RECORD
